pyOrcas/__init__.py
pyOrcas/actuator.py
pyOrcas/constants.py
pyOrcas-0.1.7.dist-info/LICENSE
pyOrcas-0.1.7.dist-info/METADATA
pyOrcas-0.1.7.dist-info/WHEEL
pyOrcas-0.1.7.dist-info/top_level.txt
pyOrcas-0.1.7.dist-info/RECORD
